{"Course Catalo": "http://guide.berkeley.edu/courses/", "AEROSPC": "http://guide.berkeley.edu/courses/aerospc/", "AFRICAM": "http://guide.berkeley.edu/courses/africam/", "A,RESEC": "http://guide.berkeley.edu/courses/a,resec/", "AMERSTD": "http://guide.berkeley.edu/courses/amerstd/", "AHMA": "http://guide.berkeley.edu/courses/ahma/", "ANTHRO": "http://guide.berkeley.edu/courses/anthro/", "AST": "http://guide.berkeley.edu/courses/ast/", "ARABIC": "http://guide.berkeley.edu/courses/arabic/", "ARCH": "http://guide.berkeley.edu/courses/arch/", "ARMENI": "http://guide.berkeley.edu/courses/armeni/", "HISTART": "http://guide.berkeley.edu/courses/histart/", "ART": "http://guide.berkeley.edu/courses/art/", "ASAMST": "http://guide.berkeley.edu/courses/asamst/", "ASIANST": "http://guide.berkeley.edu/courses/asianst/", "ASTRON": "http://guide.berkeley.edu/courses/astron/", "BANGLA": "http://guide.berkeley.edu/courses/bangla/", "BIBLIOG": "http://guide.berkeley.edu/courses/bibliog/", "BIO ENG": "http://guide.berkeley.edu/courses/bio_eng/", "BIOLOGY": "http://guide.berkeley.edu/courses/biology/", "BIOPHY": "http://guide.berkeley.edu/courses/biophy/", "BOSCRSR": "http://guide.berkeley.edu/courses/boscrsr/", "BUDDSTD": "http://guide.berkeley.edu/courses/buddstd/", "BULGARI": "http://guide.berkeley.edu/courses/bulgari/", "BURMESE": "http://guide.berkeley.edu/courses/burmese/", "EWMBA": "http://guide.berkeley.edu/courses/ewmba/", "XMBA": "http://guide.berkeley.edu/courses/xmba/", "MBA": "http://guide.berkeley.edu/courses/mba/", "PHDBA": "http://guide.berkeley.edu/courses/phdba/", "UGBA": "http://guide.berkeley.edu/courses/ugba/", "CATALAN": "http://guide.berkeley.edu/courses/catalan/", "CELTIC": "http://guide.berkeley.edu/courses/celtic/", "CHM ENG": "http://guide.berkeley.edu/courses/chm_eng/", "CHEM": "http://guide.berkeley.edu/courses/chem/", "CHICANO": "http://guide.berkeley.edu/courses/chicano/", "CHINESE": "http://guide.berkeley.edu/courses/chinese/", "CY PLAN": "http://guide.berkeley.edu/courses/cy_plan/", "CIV ENG": "http://guide.berkeley.edu/courses/civ_eng/", "CLASSIC": "http://guide.berkeley.edu/courses/classic/", "COG SCI": "http://guide.berkeley.edu/courses/cog_sci/", "COLWRIT": "http://guide.berkeley.edu/courses/colwrit/", "COMPBIO": "http://guide.berkeley.edu/courses/compbio/", "COM LIT": "http://guide.berkeley.edu/courses/com_lit/", "CMPBIO": "http://guide.berkeley.edu/courses/cmpbio/", "COMPSCI": "http://guide.berkeley.edu/courses/compsci/", "CRWRIT": "http://guide.berkeley.edu/courses/crwrit/", "CRIT TH": "http://guide.berkeley.edu/courses/crit_th/", "CUNEIF": "http://guide.berkeley.edu/courses/cuneif/", "CZECH": "http://guide.berkeley.edu/courses/czech/", "DANISH": "http://guide.berkeley.edu/courses/danish/", "DATASCI": "http://guide.berkeley.edu/courses/datasci/", "DEMOG": "http://guide.berkeley.edu/courses/demog/", "DES INV": "http://guide.berkeley.edu/courses/des_inv/", "DEV ENG": "http://guide.berkeley.edu/courses/dev_eng/", "DEVP": "http://guide.berkeley.edu/courses/devp/", "DEV STD": "http://guide.berkeley.edu/courses/dev_std/", "DUTCH": "http://guide.berkeley.edu/courses/dutch/", "EPS": "http://guide.berkeley.edu/courses/eps/", "EA LANG": "http://guide.berkeley.edu/courses/ea_lang/", "ECON": "http://guide.berkeley.edu/courses/econ/", "EDUC": "http://guide.berkeley.edu/courses/educ/", "EGYPT": "http://guide.berkeley.edu/courses/egypt/", "EECS": "http://guide.berkeley.edu/courses/eecs/", "EL ENG": "http://guide.berkeley.edu/courses/el_eng/", "ENE,RES": "http://guide.berkeley.edu/courses/ene,res/", "ENGIN": "http://guide.berkeley.edu/courses/engin/", "ENGLISH": "http://guide.berkeley.edu/courses/english/", "ENV DES": "http://guide.berkeley.edu/courses/env_des/", "ENVECON": "http://guide.berkeley.edu/courses/envecon/", "ESPM": "http://guide.berkeley.edu/courses/espm/", "ENV SCI": "http://guide.berkeley.edu/courses/env_sci/", "ETH STD": "http://guide.berkeley.edu/courses/eth_std/", "ETH GRP": "http://guide.berkeley.edu/courses/eth_grp/", "EUST": "http://guide.berkeley.edu/courses/eust/", "FILIPN": "http://guide.berkeley.edu/courses/filipn/", "FILM": "http://guide.berkeley.edu/courses/film/", "MFE": "http://guide.berkeley.edu/courses/mfe/", "FINNISH": "http://guide.berkeley.edu/courses/finnish/", "FOLKLOR": "http://guide.berkeley.edu/courses/folklor/", "FRENCH": "http://guide.berkeley.edu/courses/french/", "GWS": "http://guide.berkeley.edu/courses/gws/", "GEOG": "http://guide.berkeley.edu/courses/geog/", "GERMAN": "http://guide.berkeley.edu/courses/german/", "GMS": "http://guide.berkeley.edu/courses/gms/", "GPP": "http://guide.berkeley.edu/courses/gpp/", "GLOBAL": "http://guide.berkeley.edu/courses/global/", "GSPDP": "http://guide.berkeley.edu/courses/gspdp/", "GREEK": "http://guide.berkeley.edu/courses/greek/", "HMEDSCI": "http://guide.berkeley.edu/courses/hmedsci/", "HEBREW": "http://guide.berkeley.edu/courses/hebrew/", "HIN-URD": "http://guide.berkeley.edu/courses/hin-urd/", "HISTORY": "http://guide.berkeley.edu/courses/history/", "HUNGARI": "http://guide.berkeley.edu/courses/hungari/", "ICELAND": "http://guide.berkeley.edu/courses/iceland/", "ILA": "http://guide.berkeley.edu/courses/ila/", "IND ENG": "http://guide.berkeley.edu/courses/ind_eng/", "INFO": "http://guide.berkeley.edu/courses/info/", "INTEGBI": "http://guide.berkeley.edu/courses/integbi/", "ISF": "http://guide.berkeley.edu/courses/isf/", "IAS": "http://guide.berkeley.edu/courses/ias/", "IRANIAN": "http://guide.berkeley.edu/courses/iranian/", "ITALIAN": "http://guide.berkeley.edu/courses/italian/", "JAPAN": "http://guide.berkeley.edu/courses/japan/", "JEWISH": "http://guide.berkeley.edu/courses/jewish/", "JOURN": "http://guide.berkeley.edu/courses/journ/", "KHMER": "http://guide.berkeley.edu/courses/khmer/", "KOREAN": "http://guide.berkeley.edu/courses/korean/", "LD ARCH": "http://guide.berkeley.edu/courses/ld_arch/", "LAN PRO": "http://guide.berkeley.edu/courses/lan_pro/", "LATAMST": "http://guide.berkeley.edu/courses/latamst/", "LATIN": "http://guide.berkeley.edu/courses/latin/", "LEGALST": "http://guide.berkeley.edu/courses/legalst/", "LGBT": "http://guide.berkeley.edu/courses/lgbt/", "L&S;": "http://guide.berkeley.edu/courses/l_s/", "LINFOST": "http://guide.berkeley.edu/courses/linfost/", "LINGUIS": "http://guide.berkeley.edu/courses/linguis/", "MALAY/I": "http://guide.berkeley.edu/courses/malay_i/", "MAT SCI": "http://guide.berkeley.edu/courses/mat_sci/", "MATH": "http://guide.berkeley.edu/courses/math/", "MEC ENG": "http://guide.berkeley.edu/courses/mec_eng/", "MEDIAST": "http://guide.berkeley.edu/courses/mediast/", "MED ST": "http://guide.berkeley.edu/courses/med_st/", "M E STU": "http://guide.berkeley.edu/courses/m_e_stu/", "MIL AFF": "http://guide.berkeley.edu/courses/mil_aff/", "MIL SCI": "http://guide.berkeley.edu/courses/mil_sci/", "MCELLBI": "http://guide.berkeley.edu/courses/mcellbi/", "MONGOLN": "http://guide.berkeley.edu/courses/mongoln/", "MUSIC": "http://guide.berkeley.edu/courses/music/", "NSE": "http://guide.berkeley.edu/courses/nse/", "NATAMST": "http://guide.berkeley.edu/courses/natamst/", "NAT RES": "http://guide.berkeley.edu/courses/nat_res/", "NAV SCI": "http://guide.berkeley.edu/courses/nav_sci/", "NE STUD": "http://guide.berkeley.edu/courses/ne_stud/", "NEUROSC": "http://guide.berkeley.edu/courses/neurosc/", "NWMEDIA": "http://guide.berkeley.edu/courses/nwmedia/", "NORWEGN": "http://guide.berkeley.edu/courses/norwegn/", "NUC ENG": "http://guide.berkeley.edu/courses/nuc_eng/", "NUSCTX": "http://guide.berkeley.edu/courses/nusctx/", "OPTOM": "http://guide.berkeley.edu/courses/optom/", "PACS": "http://guide.berkeley.edu/courses/pacs/", "PERSIAN": "http://guide.berkeley.edu/courses/persian/", "PHILOS": "http://guide.berkeley.edu/courses/philos/", "PHYS ED": "http://guide.berkeley.edu/courses/phys_ed/", "PHYSICS": "http://guide.berkeley.edu/courses/physics/", "PLANTBI": "http://guide.berkeley.edu/courses/plantbi/", "POLISH": "http://guide.berkeley.edu/courses/polish/", "POLECON": "http://guide.berkeley.edu/courses/polecon/", "POL SCI": "http://guide.berkeley.edu/courses/pol_sci/", "PORTUG": "http://guide.berkeley.edu/courses/portug/", "PSYCH": "http://guide.berkeley.edu/courses/psych/", "PUB AFF": "http://guide.berkeley.edu/courses/pubaff/", "PB HLTH": "http://guide.berkeley.edu/courses/pb_hlth/", "PUB POL": "http://guide.berkeley.edu/courses/pub_pol/", "PUNJABI": "http://guide.berkeley.edu/courses/punjabi/", "RELIGST": "http://guide.berkeley.edu/courses/religst/", "RHETOR": "http://guide.berkeley.edu/courses/rhetor/", "ROMANI": "http://guide.berkeley.edu/courses/romani/", "RUSSIAN": "http://guide.berkeley.edu/courses/russian/", "SANSKR": "http://guide.berkeley.edu/courses/sanskr/", "SCANDIN": "http://guide.berkeley.edu/courses/scandin/", "SCMATHE": "http://guide.berkeley.edu/courses/scmathe/", "STS": "http://guide.berkeley.edu/courses/sts/", "SEMITIC": "http://guide.berkeley.edu/courses/semitic/", "SLAVIC": "http://guide.berkeley.edu/courses/slavic/", "SOC WEL": "http://guide.berkeley.edu/courses/soc_wel/", "SOCIOL": "http://guide.berkeley.edu/courses/sociol/", "S,SEASN": "http://guide.berkeley.edu/courses/s,seasn/", "S ASIAN": "http://guide.berkeley.edu/courses/s_asian/", "SEASIAN": "http://guide.berkeley.edu/courses/seasian/", "SPANISH": "http://guide.berkeley.edu/courses/spanish/", "EDUCSPE": "http://guide.berkeley.edu/courses/educspe/", "STAT": "http://guide.berkeley.edu/courses/stat/", "SWEDISH": "http://guide.berkeley.edu/courses/swedish/", "TAMIL": "http://guide.berkeley.edu/courses/tamil/", "TELUGU": "http://guide.berkeley.edu/courses/telugu/", "THAI": "http://guide.berkeley.edu/courses/thai/", "THEATER": "http://guide.berkeley.edu/courses/theater/", "TIBETAN": "http://guide.berkeley.edu/courses/tibetan/", "TURKISH": "http://guide.berkeley.edu/courses/turkish/", "UGIS": "http://guide.berkeley.edu/courses/ugis/", "VIETNMS": "http://guide.berkeley.edu/courses/vietnms/", "VIS SCI": "http://guide.berkeley.edu/courses/vis_sci/", "VIS STD": "http://guide.berkeley.edu/courses/vis_std/", "YIDDISH": "http://guide.berkeley.edu/courses/yiddish/"}